{
  "main": {
    "id": "81148cb7ea6c89a9",
    "type": "split",
    "children": [
      {
        "id": "ca1e68eeac751281",
        "type": "tabs",
        "children": [
          {
            "id": "fcd9003accbdf525",
            "type": "leaf",
            "state": {
              "type": "markdown",
              "state": {
                "file": "_AI-Setup/work_efforts/active/202503161730_codebase_streamlining_for_version_update/202503161730_codebase_streamlining_for_version_update.md",
                "mode": "source",
                "source": false
              },
              "icon": "lucide-file",
              "title": "202503161730_codebase_streamlining_for_version_update"
            }
          }
        ]
      }
    ],
    "direction": "vertical"
  },
  "left": {
    "id": "47af2ec38d0d6c45",
    "type": "split",
    "children": [
      {
        "id": "e9f540a04edcae09",
        "type": "tabs",
        "children": [
          {
            "id": "a2f903a963a2b432",
            "type": "leaf",
            "state": {
              "type": "file-explorer",
              "state": {
                "sortOrder": "alphabetical",
                "autoReveal": false
              },
              "icon": "lucide-folder-closed",
              "title": "Files"
            }
          },
          {
            "id": "1e1491a3ed80af77",
            "type": "leaf",
            "state": {
              "type": "search",
              "state": {
                "query": "",
                "matchingCase": false,
                "explainSearch": false,
                "collapseAll": false,
                "extraContext": false,
                "sortOrder": "alphabetical"
              },
              "icon": "lucide-search",
              "title": "Search"
            }
          },
          {
            "id": "26a79087981bb52c",
            "type": "leaf",
            "state": {
              "type": "bookmarks",
              "state": {},
              "icon": "lucide-bookmark",
              "title": "Bookmarks"
            }
          }
        ]
      }
    ],
    "direction": "horizontal",
    "width": 300
  },
  "right": {
    "id": "f4e3536d36dbef66",
    "type": "split",
    "children": [
      {
        "id": "a3f1548a765e5fc2",
        "type": "tabs",
        "children": [
          {
            "id": "cad15ec4b4ffebac",
            "type": "leaf",
            "state": {
              "type": "backlink",
              "state": {
                "file": "_AI-Setup/work_efforts/active/202503091038_code_modularization___breaking_up_monolithic_files.md",
                "collapseAll": false,
                "extraContext": false,
                "sortOrder": "alphabetical",
                "showSearch": false,
                "searchQuery": "",
                "backlinkCollapsed": false,
                "unlinkedCollapsed": true
              },
              "icon": "links-coming-in",
              "title": "Backlinks for 202503091038_code_modularization___breaking_up_monolithic_files"
            }
          },
          {
            "id": "2f8220aaa8b85871",
            "type": "leaf",
            "state": {
              "type": "outgoing-link",
              "state": {
                "file": "_AI-Setup/work_efforts/active/202503091038_code_modularization___breaking_up_monolithic_files.md",
                "linksCollapsed": false,
                "unlinkedCollapsed": true
              },
              "icon": "links-going-out",
              "title": "Outgoing links from 202503091038_code_modularization___breaking_up_monolithic_files"
            }
          },
          {
            "id": "d4738cd59c051575",
            "type": "leaf",
            "state": {
              "type": "tag",
              "state": {
                "sortOrder": "frequency",
                "useHierarchy": true,
                "showSearch": false,
                "searchQuery": ""
              },
              "icon": "lucide-tags",
              "title": "Tags"
            }
          },
          {
            "id": "2d7af217ccb7de1a",
            "type": "leaf",
            "state": {
              "type": "outline",
              "state": {
                "file": "_AI-Setup/work_efforts/active/202503091038_code_modularization___breaking_up_monolithic_files.md",
                "followCursor": false,
                "showSearch": false,
                "searchQuery": ""
              },
              "icon": "lucide-list",
              "title": "Outline of 202503091038_code_modularization___breaking_up_monolithic_files"
            }
          }
        ]
      }
    ],
    "direction": "horizontal",
    "width": 300,
    "collapsed": true
  },
  "left-ribbon": {
    "hiddenItems": {
      "switcher:Open quick switcher": false,
      "graph:Open graph view": false,
      "canvas:Create new canvas": false,
      "daily-notes:Open today's daily note": false,
      "templates:Insert template": false,
      "command-palette:Open command palette": false
    }
  },
  "active": "fcd9003accbdf525",
  "lastOpenFiles": [
    "_AI-Setup/work_efforts/active/202503161730_codebase_streamlining_for_version_update/scripts/test_typing.py.bak",
    "_AI-Setup/work_efforts/active/202503161730_codebase_streamlining_for_version_update/scripts/batch_cleanup_imports.py",
    "_AI-Setup/work_efforts/active/202503161730_codebase_streamlining_for_version_update/project_structure_map.md",
    "_AI-Setup/work_efforts/active/202503161730_codebase_streamlining_for_version_update/summary.md",
    "_AI-Setup/work_efforts/active/202503161730_codebase_streamlining_for_version_update/scripts/test_typing.py",
    "_AI-Setup/work_efforts/active/202503161730_codebase_streamlining_for_version_update/scripts/test_cleanup2.py.bak",
    "_AI-Setup/work_efforts/active/202503161730_codebase_streamlining_for_version_update/scripts/test_cleanup2.py",
    "_AI-Setup/work_efforts/active/202503161730_codebase_streamlining_for_version_update/scripts/test_cleanup.py.bak",
    "_AI-Setup/work_efforts/active/202503161730_codebase_streamlining_for_version_update/scripts/test_cleanup.py",
    "_AI-Setup/work_efforts/active/202503161730_codebase_streamlining_for_version_update/scripts/cleanup_unused_imports.py",
    "_AI-Setup/work_efforts/active/202503161730_codebase_streamlining_for_version_update/docs/unused_imports_analysis.md",
    "_AI-Setup/work_efforts/active/202503161730_codebase_streamlining_for_version_update/docs/unused_imports_work_efforts.txt",
    "_AI-Setup/work_efforts/active/202503161730_codebase_streamlining_for_version_update/docs/unused_imports_tests.txt",
    "_AI-Setup/work_efforts/active/202503161730_codebase_streamlining_for_version_update/docs/unused_imports_src.txt",
    "_AI-Setup/work_efforts/active/202503161730_codebase_streamlining_for_version_update/docs/detect_unused_imports.md",
    "_AI-Setup/work_efforts/active/202503161730_codebase_streamlining_for_version_update/scripts/README.md",
    "src/code_conductor/work_efforts/templates/work-effort-template.md",
    "_AI-Setup/work_efforts/active/202503081145_add_work_efforts_folder_to_ai_setup/202503081145_add_work_efforts_folder_to_ai_setup.md",
    "_AI-Setup/work_efforts/active/202503160742_automated_workflow_scripts/202503160742_automated_workflow_scripts.md",
    "_AI-Setup/work_efforts/active/202503062014_getting_started/202503062014_getting_started.md",
    "_AI-Setup/work_efforts/active/202503160900_ai_setup_directory_rename/202503160900_ai_setup_directory_rename.md",
    "_AI-Setup/work_efforts/active/202503091252_getting_started/202503091252_getting_started.md",
    "_AI-Setup/work_efforts/active/202503091038_code_modularization___breaking_up_monolithic_files/202503091038_code_modularization___breaking_up_monolithic_files.md",
    "_AI-Setup/work_efforts/active/202503062029_install_the_package_again/202503062029_install_the_package_again.md",
    "_AI-Setup/work_efforts/active/202503160633_obsidian_style_document_linking/202503160633_obsidian_style_document_linking.md",
    "_AI-Setup/work_efforts/active/202503160805_work_effort_context_retrieval/202503160805_work_effort_context_retrieval.md",
    "_AI-Setup/work_efforts/active/202503160750_template_integration/202503160750_template_integration.md",
    "_AI-Setup/work_efforts/active/202503160820_project_restructuring/202503160820_project_restructuring.md",
    "_AI-Setup/work_efforts/active/202503091306_test_inside_ai-setup/202503091306_test_inside_ai-setup.md",
    "_AI-Setup/work_efforts/active/202503091238_test_in_current_directory/202503091238_test_in_current_directory.md",
    "_AI-Setup/work_efforts/active/202503071956_global_installation_of_ai_setup_package/202503071956_global_installation_of_ai_setup_package.md",
    "_AI-Setup/work_efforts/active/202503062014_untitled/202503062014_untitled.md",
    "_AI-Setup/work_efforts/active/202503160716_work_node_creation_workflow/202503160716_work_node_creation_workflow.md",
    "_AI-Setup/work_efforts/active/202503062041_using_ai_setup_command/202503062041_using_ai_setup_command.md",
    "_AI-Setup/work_efforts/active/202503091415_getting_started/202503091415_getting_started.md",
    "_AI-Setup/work_efforts/active/202503091259_getting_started/202503091259_getting_started.md"
  ]
}